pipoke/__init__.py
pipoke/distribution.py
pipoke/misc.py
pipoke/pkg_diagnosis.py
pipoke/pkg_vs_words.py
pipoke/pypi_store.py
pipoke/word_conditions.py
pipoke-0.0.23.dist-info/LICENSE
pipoke-0.0.23.dist-info/METADATA
pipoke-0.0.23.dist-info/WHEEL
pipoke-0.0.23.dist-info/entry_points.txt
pipoke-0.0.23.dist-info/top_level.txt
pipoke-0.0.23.dist-info/RECORD
