Metadata-Version: 2.1
Name: pipoke
Version: 0.0.23
Summary: Utils to acquire stuff from pypi and interrogate it
Home-page: https://github.com/thorwhalen/pipoke
License: Apache Software License
Keywords: pip,pypi,packaging
Platform: any
License-File: LICENSE
Requires-Dist: bs4
Requires-Dist: requests
Requires-Dist: argh
Requires-Dist: py2store
Requires-Dist: i2
Requires-Dist: yp
Requires-Dist: packaging
Requires-Dist: nltk
Requires-Dist: dol
